flyover/__init__.py
flyover/__main__.py
flyover/extractor/__init__.py
flyover/extractor/glue_extractor.py
flyover/loader/__init__.py
flyover/loader/carte_loader.py
flyover/model/__init__.py
flyover/model/carte_table_model.py
flyover/model/job_metadata.py
flyover/utils/__init__.py
flyover/utils/config_parser.py
flyover/utils/frontmatter.py
flyover-0.1.7.dist-info/LICENSE
flyover-0.1.7.dist-info/METADATA
flyover-0.1.7.dist-info/WHEEL
flyover-0.1.7.dist-info/entry_points.txt
flyover-0.1.7.dist-info/top_level.txt
flyover-0.1.7.dist-info/RECORD
