Metadata-Version: 2.1
Name: flyover
Version: 0.1.7
Summary: Carte Flyover – extract metadata from data storage into files
Home-page: https://github.com/CarteData/carte-flyover
Maintainer: Balint Haller
Maintainer-email: balint@haller.io
License: UNKNOWN
Platform: UNKNOWN
Classifier: Programming Language :: Python :: 3.6
Classifier: Programming Language :: Python :: 3.7
Classifier: Programming Language :: Python :: 3.8
Requires-Python: >=3.6
Requires-Dist: boto3 (>=1.16.25)
Requires-Dist: pyhocon (>=0.3.57)
Requires-Dist: amundsen-databuilder (>=4.0.3)
Requires-Dist: ruamel.yaml (>=0.16.12)
